{"cameraMode":{"drawMode":0,"name":"Shaded","section":"Shading Mode"},"sceneLighting":true,"audioPlay":false,"sceneViewState":{"m_AlwaysRefresh":false,"showFog":true,"showSkybox":true,"showFlares":true,"showImageEffects":true,"showParticleSystems":true,"showVisualEffectGraphs":true,"m_FxEnabled":true},"in2DMode":false,"pivot":{"x":-0.30523625016212466,"y":4.983931064605713,"z":-9.194334030151368},"rotation":{"x":-0.1021241694688797,"y":0.012529583647847176,"z":-0.001289504230953753,"w":-0.9947004914283752},"size":9.629950523376465,"orthographic":false}